Metadata-Version: 2.1
Name: F1-data
Version: 0.0.1
Summary: Formula 1 data analysis based on FastF1 library
Home-page: https://www.leonardorama.tk
Author: Leonardo Ramazzotti
License: MIT
Keywords: formula1
Platform: UNKNOWN
Classifier: Development Status :: 5 - Production/Stable
Classifier:  Intended Audience :: Education
Classifier: Operating System :: Microsoft :: Windows :: Windows 10
Classifier: License :: OSI Approved :: MIT License
Classifier: Programming Language :: Python :: 3
License-File: LICENSE.txt
